README.md
setup.py
DoxyXML/__init__.py
DoxyXML/_common_parser.py
DoxyXML/class_member.py
DoxyXML/class_obj.py
DoxyXML/index_parser.py
DoxyXML.egg-info/PKG-INFO
DoxyXML.egg-info/SOURCES.txt
DoxyXML.egg-info/dependency_links.txt
DoxyXML.egg-info/top_level.txt
tests/__init__.py
tests/test_class_obj.py
tests/test_index_parser.py
tests/test_pylint_utl.py
tests/quality/__init__.py
tests/quality/pylint_utl.py