Metadata-Version: 2.1
Name: DoxyXML
Version: 0.1.0
Summary: Parse XML documentation generated by Doxygen
Home-page: https://gitlab.com/xcoponet/doxyxml
Author: Xavier Coponet
Author-email: xavier.coponet@gmail.com
License: MIT
Project-URL: Documentation, https://xcoponet.gitlab.io/doxyxml/
Platform: UNKNOWN
Classifier: Development Status :: 2 - Pre-Alpha
Classifier: Programming Language :: Python :: 3
Classifier: License :: OSI Approved :: MIT License
Classifier: Operating System :: OS Independent
